[{"anonymous":false,"inputs":[{"indexed":true,"internalType":"address","name":"_caller","type":"address"},{"indexed":false,"internalType":"uint256","name":"_amount","type":"uint256"}],"name":"Allocate","type":"event"},{"anonymous":false,"inputs":[{"indexed":false,"internalType":"uint256","name":"_buffer","type":"uint256"}],"name":"BufferUpdate","type":"event"},{"anonymous":false,"inputs":[{"indexed":false,"internalType":"uint256","name":"_incentiveAmount","type":"uint256"}],"name":"IncentiveAmountUpdate","type":"event"},{"anonymous":false,"inputs":[{"indexed":true,"internalType":"address","name":"_to","type":"address"},{"indexed":false,"internalType":"uint256","name":"_amountIn","type":"uint256"},{"indexed":false,"internalType":"uint256","name":"_amountOut","type":"uint256"}],"name":"Purchase","type":"event"},{"anonymous":false,"inputs":[{"indexed":false,"internalType":"uint256","name":"_scale","type":"uint256"}],"name":"ScaleUpdate","type":"event"},{"inputs":[{"internalType":"address","name":"to","type":"address"},{"internalType":"uint256","name":"amountIn","type":"uint256"}],"name":"purchase","outputs":[{"internalType":"uint256","name":"amountOut","type":"uint256"}],"stateMutability":"payable","type":"function"},{"inputs":[],"name":"allocate","outputs":[],"stateMutability":"nonpayable","type":"function"},{"inputs":[{"internalType":"uint256","name":"_buffer","type":"uint256"}],"name":"setBuffer","outputs":[],"stateMutability":"nonpayable","type":"function"},{"inputs":[{"internalType":"uint256","name":"_scale","type":"uint256"}],"name":"setScale","outputs":[],"stateMutability":"nonpayable","type":"function"},{"inputs":[{"internalType":"address[]","name":"pcvDeposits","type":"address[]"},{"internalType":"uint256[]","name":"ratios","type":"uint256[]"}],"name":"setAllocation","outputs":[],"stateMutability":"nonpayable","type":"function"},{"inputs":[{"internalType":"uint256","name":"_incentiveAmount","type":"uint256"}],"name":"setIncentiveAmount","outputs":[],"stateMutability":"nonpayable","type":"function"},{"inputs":[{"internalType":"uint256","name":"_frequency","type":"uint256"}],"name":"setIncentiveFrequency","outputs":[],"stateMutability":"nonpayable","type":"function"},{"inputs":[],"name":"getCurrentPrice","outputs":[{"components":[{"internalType":"uint256","name":"value","type":"uint256"}],"internalType":"struct Decimal.D256","name":"","type":"tuple"}],"stateMutability":"view","type":"function"},{"inputs":[{"internalType":"uint256","name":"amountIn","type":"uint256"}],"name":"getAverageUSDPrice","outputs":[{"components":[{"internalType":"uint256","name":"value","type":"uint256"}],"internalType":"struct Decimal.D256","name":"","type":"tuple"}],"stateMutability":"view","type":"function"},{"inputs":[{"internalType":"uint256","name":"amountIn","type":"uint256"}],"name":"getAmountOut","outputs":[{"internalType":"uint256","name":"amountOut","type":"uint256"}],"stateMutability":"view","type":"function"},{"inputs":[],"name":"scale","outputs":[{"internalType":"uint256","name":"","type":"uint256"}],"stateMutability":"view","type":"function"},{"inputs":[],"name":"atScale","outputs":[{"internalType":"bool","name":"","type":"bool"}],"stateMutability":"view","type":"function"},{"inputs":[],"name":"buffer","outputs":[{"internalType":"uint256","name":"","type":"uint256"}],"stateMutability":"view","type":"function"},{"inputs":[],"name":"totalPurchased","outputs":[{"internalType":"uint256","name":"","type":"uint256"}],"stateMutability":"view","type":"function"},{"inputs":[],"name":"getTotalPCVHeld","outputs":[{"internalType":"uint256","name":"","type":"uint256"}],"stateMutability":"view","type":"function"},{"inputs":[],"name":"incentiveAmount","outputs":[{"internalType":"uint256","name":"","type":"uint256"}],"stateMutability":"view","type":"function"}]